src/__init__.py
src/reverse_diagrams.py
src/version.py
src/aws/__init__.py
src/aws/describe_identity_store.py
src/aws/describe_organization.py
src/aws/describe_sso.py
src/banner/__init__.py
src/banner/banner.py
src/dgms/__init__.py
src/dgms/graph_mapper.py
src/dgms/graph_template.py
src/reports/__init__.py
src/reports/console_view.py
src/reports/save_results.py
src/reports/tes.py
reverse_diagrams-1.3.4.dist-info/METADATA
reverse_diagrams-1.3.4.dist-info/WHEEL
reverse_diagrams-1.3.4.dist-info/entry_points.txt
reverse_diagrams-1.3.4.dist-info/licenses/LICENSE
reverse_diagrams-1.3.4.dist-info/RECORD
