Metadata-Version: 2.3
Name: reverse_diagrams
Version: 1.3.4
Summary: Continuous Documentation Tool - Documentation as Code Tool -   This package create reverse diagrams  based on your current state in your cloud environment using diagrams library
Project-URL: Homepage, https://github.com/velez94/reverse_diagrams
Project-URL: Bug Tracker, https://github.com/velez94/reverse_diagrams/issues
Author-email: Alejandro Velez <avelez@labvel.io>
License: Copyright [2024] [Alejandro Velez]
License-File: LICENSE
Classifier: Operating System :: OS Independent
Classifier: Programming Language :: Python :: 3
Requires-Python: >=3.8
Requires-Dist: argcomplete>=3.4.0
Requires-Dist: boto3>=1.26.44
Requires-Dist: colorama>=0.4.4
Requires-Dist: diagrams>=0.23.4
Requires-Dist: emoji>=2.2.0
Requires-Dist: inquirer>=3.1.4
Requires-Dist: rich>=13.7.0
